<?xml version="1.0" encoding="UTF-8"?>
<record_update table="sp_instance">
    <sp_instance action="INSERT_OR_UPDATE">
        <active>true</active>
        <class_name/>
        <color>default</color>
        <css/>
        <glyph/>
        <id/>
        <order>0</order>
        <short_description/>
        <size>md</size>
        <sp_column display_value="3">485337724fa2b60057364beab110c73b</sp_column>
        <sp_widget display_value="Event News">c2ba3f7a4f62b6004677bd728110c724</sp_widget>
        <sys_class_name>sp_instance</sys_class_name>
        <sys_created_by>admin</sys_created_by>
        <sys_created_on>2017-05-09 20:17:12</sys_created_on>
        <sys_customer_update>true</sys_customer_update>
        <sys_id>ca0f373e4f62b6004677bd728110c7e0</sys_id>
        <sys_mod_count>2</sys_mod_count>
        <sys_name>Fundraising Events</sys_name>
        <sys_package display_value="Charitable Events" source="x_snc_charitable_e">ac82b2fe4fae760057364beab110c72b</sys_package>
        <sys_policy/>
        <sys_replace_on_upgrade>false</sys_replace_on_upgrade>
        <sys_scope display_value="Charitable Events">ac82b2fe4fae760057364beab110c72b</sys_scope>
        <sys_update_name>sp_instance_ca0f373e4f62b6004677bd728110c7e0</sys_update_name>
        <sys_updated_by>admin</sys_updated_by>
        <sys_updated_on>2017-05-09 20:17:31</sys_updated_on>
        <title>Fundraising Events</title>
        <url/>
        <widget_parameters><![CDATA[{
	"max_number": {
		"value": null,
		"displayValue": ""
	},
	"kb_category": {
		"value": "cf0433b64f62b6004677bd728110c764",
		"displayValue": "fundraising"
	}
}]]></widget_parameters>
    </sp_instance>
    <sys_translated_text action="delete_multiple" query="documentkey=ca0f373e4f62b6004677bd728110c7e0"/>
</record_update>
